[{"TravelLokaId":9000000927447,"HotelName":"Nhan Hoa Hotel","Country":"Vietnam","City":"Thanh Xuan District","Address":"66/116 Nhan Hoa, Nhan Chinh","Lat":21.0024842,"Lng":105.8069142},{"TravelLokaId":9000000927460,"HotelName":"An Binh House Saigon","Country":"Vietnam","City":"District 10","Address":"457/73 Cach Mang Thang 8","Lat":10.7826541,"Lng":106.672127},{"TravelLokaId":9000000927512,"HotelName":"Friday Luxury Apartment","Country":"Vietnam","City":"District 1","Address":"102/22 Cong Quynh","Lat":10.764822,"Lng":106.691086},{"TravelLokaId":9000000927521,"HotelName":"Let'Stay Homestay Dalat","Country":"Vietnam","City":"Da Lat","Address":"60C Van Hanh, Ward 8","Lat":11.9626187,"Lng":108.4479662},{"TravelLokaId":9000000927526,"HotelName":"Bao Lac Homestay","Country":"Vietnam","City":"Bao Lac District","Address":"Kha Rao Hamlet, Khanh Xuan","Lat":22.934047875,"Lng":105.718745085},{"TravelLokaId":9000000927556,"HotelName":"My Little Pig Home","Country":"Vietnam","City":"Son Tra District","Address":"04 An Nhơn 1","Lat":16.0704922,"Lng":108.2330285},{"TravelLokaId":9000000927561,"HotelName":"Anh Tien Hotel Dalat","Country":"Vietnam","City":"Da Lat","Address":"R12 Nguyen Thi Nghia","Lat":11.9479235,"Lng":108.4405675},{"TravelLokaId":9000000927568,"HotelName":"Lyn House Pool Villa - Homestay in Ecopark","Country":"Vietnam","City":"Van Giang District","Address":"Ecopark Xuan Quan, Van Giang District","Lat":20.9683812,"Lng":105.9341334},{"TravelLokaId":9000000927570,"HotelName":"Mega View Homestay","Country":"Vietnam","City":"Sa Pa District","Address":"24 Ngo Cau May","Lat":22.331890259,"Lng":103.843444344},{"TravelLokaId":9000000927649,"HotelName":"Aliis Home Dalat","Country":"Vietnam","City":"Da Lat","Address":"52 An Duong Vuong st., Ward 2, Dalat City","Lat":11.952184313,"Lng":108.435545415},{"TravelLokaId":9000000927651,"HotelName":"Lien's Hotel Dalat","Country":"Vietnam","City":"Da Lat","Address":"279 Phan Đình Phùng, Phường 2, Thành phố Đà Lạt, Lâm Đồng","Lat":11.9496331,"Lng":108.4349968},{"TravelLokaId":9000000927662,"HotelName":"Hoan My Resort Ninh Chu","Country":"Vietnam","City":"Phan Rang - Thap Cham City","Address":"Duong Yen Ninh, Phuong My Dinh, Thành phố phan rang tháp chàm , Ninh Thuận","Lat":11.5741134,"Lng":109.0242702},{"TravelLokaId":9000000927665,"HotelName":"Quang Chung Hotel","Country":"Vietnam","City":"Thanh Xuan District","Address":"56 Le Van Thiem, Nhan Chinh","Lat":21.0026032,"Lng":105.8025587},{"TravelLokaId":9000000927669,"HotelName":"Mermaid Seaview Apartment Vungtau","Country":"Vietnam","City":"Vung Tau City","Address":"No.11 Le Hong Phong (noi dai), Thang Tam Ward","Lat":10.34647614,"Lng":107.096008289},{"TravelLokaId":9000000927680,"HotelName":"The Flamboyant - Serviced Apartments","Country":"Vietnam","City":"Hong Bang District","Address":"Vinhomes Imperia, BH 04-21, Manhattan 11 Street","Lat":20.8595313,"Lng":106.666993},{"TravelLokaId":9000000927693,"HotelName":"Christy Home Dalat","Country":"Vietnam","City":"Da Lat","Address":"41 An Binh","Lat":11.927901,"Lng":108.437412},{"TravelLokaId":9000000927700,"HotelName":"Meander Saigon","Country":"Vietnam","City":"District 1","Address":"3B Ly Tu Trong, Ben Nghe Ward","Lat":10.7825564,"Lng":106.7053679},{"TravelLokaId":9000000927704,"HotelName":"The May Hotel Phu Quoc","Country":"Vietnam","City":"Phu Quoc","Address":"Tran Hung Dao, Cua Lap, Duong To","Lat":10.1879048,"Lng":103.9664328},{"TravelLokaId":9000000927709,"HotelName":"Linh Apartment - Sai Gon Royal","Country":"Vietnam","City":"District 4","Address":"34 - 35 Ben Van Don","Lat":10.7670895,"Lng":106.7036913},{"TravelLokaId":9000000927718,"HotelName":"Song Dai Duong Villa 2 - Villa FLC Sam Son","Country":"Vietnam","City":"Thanh Hoa City","Address":"Villa FLC Sam Son Ngoc Trai NT34","Lat":19.7758718,"Lng":105.8411804},{"TravelLokaId":9000000927720,"HotelName":"Nha Khach Binh Phuoc","Country":"Vietnam","City":"Dong Xoai Town","Address":"Le Duan","Lat":11.541883,"Lng":106.886887},{"TravelLokaId":9000000927732,"HotelName":"22Housing Apartment 39 Linh Lang","Country":"Vietnam","City":"Ba Dinh District","Address":"39 Linh Lang, Ba Dinh","Lat":21.0356395,"Lng":105.8105365},{"TravelLokaId":9000000927734,"HotelName":"Tan Son Nhat Con Dao Hotel","Country":"Vietnam","City":"Con Dao (Hon Son) District","Address":"Nguyen Hue","Lat":8.686502425,"Lng":106.613366604},{"TravelLokaId":9000000927747,"HotelName":"Phuc Loc Tho Hotel Dalat","Country":"Vietnam","City":"Da Lat","Address":"21A Duong 3/4","Lat":11.9325247,"Lng":108.4455163},{"TravelLokaId":9000000927751,"HotelName":"Calypso","Country":"Vietnam","City":"District 2","Address":"Street 30, Tran Nao","Lat":10.792115564,"Lng":106.727698346},{"TravelLokaId":9000000927792,"HotelName":"Sun Valley Hotel Resort Dalat","Country":"Vietnam","City":"Da Lat","Address":"139/7 Xo Viet Nghe Tinh","Lat":11.96789563,"Lng":108.428851822},{"TravelLokaId":9000000927793,"HotelName":"Meo House","Country":"Vietnam","City":"Da Lat","Address":"Alley 5, Thong Thien Hoc Street","Lat":11.9523052,"Lng":108.437944},{"TravelLokaId":9000000927796,"HotelName":"Vera Saigon Apartments - Vinhomes Central Park","Country":"Vietnam","City":"Binh Thanh District","Address":"720A Dien Bien Phu","Lat":10.7978156,"Lng":106.7201348},{"TravelLokaId":9000000927797,"HotelName":"22Housing Apartment 20 Linh Lang","Country":"Vietnam","City":"Ba Dinh District","Address":"20 Linh Lang, Ba Dinh","Lat":21.0365919,"Lng":105.810335},{"TravelLokaId":9000000927840,"HotelName":"Hoang Minh Hotel","Country":"Vietnam","City":"Tan Binh District","Address":"201 Cong Hoa","Lat":10.8017938,"Lng":106.6465506},{"TravelLokaId":9000000927843,"HotelName":"Phong Nha Hotel","Country":"Vietnam","City":"Phu Quoc","Address":"Group 1, Cua Lap","Lat":10.177610689,"Lng":103.973799348},{"TravelLokaId":9000000927848,"HotelName":"Ben's House Capsule","Country":"Vietnam","City":"Da Lat","Address":"61 Bach Dang","Lat":11.9635968,"Lng":108.4259939},{"TravelLokaId":9000000927853,"HotelName":"El Ocaso Hotel and Apartments","Country":"Vietnam","City":"District 7","Address":"No. 22 Duong Noi khu Hung Phuoc 2, phuong Tan Phong","Lat":10.7316164,"Lng":106.7077294},{"TravelLokaId":9000000927854,"HotelName":"Cozy Hotel Dalat","Country":"Vietnam","City":"Da Lat","Address":"Lo B1, KQH Phan Lo Phu Dong Thien Vuong","Lat":11.9610381,"Lng":108.4430884},{"TravelLokaId":9000000927883,"HotelName":"Ayatana Mansion Vung Tau","Country":"Vietnam","City":"Vung Tau City","Address":"21 Vi Ba","Lat":10.3564416,"Lng":107.073226},{"TravelLokaId":9000000927894,"HotelName":"GIC Airport Yen The","Country":"Vietnam","City":"Tan Binh District","Address":"60/24 Yen The","Lat":10.8119264,"Lng":106.6686114},{"TravelLokaId":9000000927926,"HotelName":"The Empire Hotel","Country":"Vietnam","City":"Phu Quoc","Address":"09 Ly Tu Trong","Lat":10.2159623,"Lng":103.9604109},{"TravelLokaId":9000000927929,"HotelName":"Cityhouse - Kim Nguyen apartment & hotel","Country":"Vietnam","City":"Phu Nhuan District","Address":"3 Truong Quoc Dung Ward 8, Phu Nhuan District","Lat":10.7990941,"Lng":106.672997},{"TravelLokaId":9000000927947,"HotelName":"TTR Vincent Hotel","Country":"Vietnam","City":"Da Lat","Address":"26 Tran Le","Lat":11.9366013,"Lng":108.4270106},{"TravelLokaId":9000000927969,"HotelName":"Cona Hotel Con Phung Ben Tre","Country":"Vietnam","City":"Chau Thanh District","Address":"Hamlet 10, Tan Thach Commune","Lat":10.336512,"Lng":106.3683821},{"TravelLokaId":9000000927976,"HotelName":"Cozy Riverview","Country":"Vietnam","City":"District 1","Address":"214/19/50 Nguyen Van Nguyen","Lat":10.792688017,"Lng":106.686857641},{"TravelLokaId":9000000927980,"HotelName":"Hanoi Carina Hotel","Country":"Vietnam","City":"Hoan Kiem District","Address":"16A Trung Yen Lane","Lat":21.0335377,"Lng":105.8522093},{"TravelLokaId":9000000927988,"HotelName":"La Fleur Premium Central Apartment","Country":"Vietnam","City":"Da Lat","Address":"5-7 Trần Phú","Lat":11.9368235,"Lng":108.4395947},{"TravelLokaId":9000000928001,"HotelName":"Panorama Central Nha Trang","Country":"Vietnam","City":"Nha Trang","Address":"2 Nguyen Thi Minh Khai","Lat":12.2387255,"Lng":109.1953283},{"TravelLokaId":9000000928003,"HotelName":"Dalat Paradise Hotel","Country":"Vietnam","City":"Da Lat","Address":"28 Ba Trieu street, ward 4, Dalat, Lam Dong, Vietnam","Lat":11.9375309,"Lng":108.4335975},{"TravelLokaId":9000000928005,"HotelName":"Maximilan Danang Beach Hotel - Buy Now Stay Later","Country":"Vietnam","City":"Son Tra District","Address":"222 Vo Nguyen Giap","Lat":16.0670011,"Lng":108.2451979},{"TravelLokaId":9000000928017,"HotelName":"Thai Ha GuestHouse Dalat","Country":"Vietnam","City":"Da Lat","Address":"27 Nguyen Thi Nghia, Ward 2","Lat":11.949225668,"Lng":108.44042033},{"TravelLokaId":9000000928027,"HotelName":"22Housing Apartment 81 Linh Lang","Country":"Vietnam","City":"Ba Dinh District","Address":"No 27, Lane 81, Linh Lang Street","Lat":21.0333161,"Lng":105.8106552},{"TravelLokaId":9000000928030,"HotelName":"ZoZo Apartment - 145 Phan Chu Trinh","Country":"Vietnam","City":"Vung Tau City","Address":"145 Phan Chu Trinh","Lat":10.329884,"Lng":107.0867898},{"TravelLokaId":9000000928031,"HotelName":"ZoZo Apartment - Son Thinh 1","Country":"Vietnam","City":"Vung Tau City","Address":"23D Thuy Van","Lat":10.3302509,"Lng":107.0882343},{"TravelLokaId":9000000928053,"HotelName":"EVELYN HOTEL DANANG","Country":"Vietnam","City":"Hai Chau District","Address":"38 Hung Vuong Da Nang","Lat":16.0686672,"Lng":108.2240161},{"TravelLokaId":9000000928055,"HotelName":"OHome 75  Da Nang - Managed by Chiic Vacation","Country":"Vietnam","City":"Son Tra District","Address":"75 Luong The Vinh","Lat":16.0638186,"Lng":108.237893},{"TravelLokaId":9000000928061,"HotelName":"Hiep Thanh Hotel Dalat","Country":"Vietnam","City":"Da Lat","Address":"68 Me Linh, ward 9","Lat":11.961473329,"Lng":108.471796811},{"TravelLokaId":9000000928110,"HotelName":"Little Room in Dalat","Country":"Vietnam","City":"Da Lat","Address":"F2-C5 Nguyen Trung Truc","Lat":11.9305781,"Lng":108.4349272},{"TravelLokaId":9000000928112,"HotelName":"Lotus Home","Country":"Vietnam","City":"Phu Quoc","Address":"Cay Sao, Ham Ninh","Lat":10.2203805,"Lng":104.0722189},{"TravelLokaId":9000000928117,"HotelName":"Kypyny Cosy House","Country":"Vietnam","City":"Hue City","Address":"130 Le Ngo Cat Thuy Xuan","Lat":16.4358187,"Lng":107.5637763},{"TravelLokaId":9000000928188,"HotelName":"Napoly Hotel","Country":"Vietnam","City":"Vung Tau City","Address":"54 Pho Duc Chinh  Thang Tam TP Vung Tau","Lat":10.3380296,"Lng":107.0885147},{"TravelLokaId":9000000928207,"HotelName":"LARA HOTEL LONG XUYEN","Country":"Vietnam","City":"Long Xuyen City","Address":"46 - 48 Hung Vuong","Lat":10.3790347,"Lng":105.4417915},{"TravelLokaId":9000000928212,"HotelName":"The View Hotel","Country":"Vietnam","City":"Nha Trang","Address":"D16-17-16 KĐT Hưng Thịnh, Cam Hải Đông, Cam Lâm, Khánh Hòa","Lat":12.119777639,"Lng":109.188283968},{"TravelLokaId":9000000928215,"HotelName":"Cornelia Hotel and Apartment","Country":"Vietnam","City":"Binh Thanh District","Address":"236/29/2L Dien Bien Phu","Lat":10.794724,"Lng":106.701173}]