[{"TravelLokaId":9000000958698,"HotelName":"Hoi An Hometown Villa","Country":"Vietnam","City":"Hoi An","Address":"Huỳnh Thúc Kháng, Cẩm Hà, Hội An","Lat":15.896297515,"Lng":108.321126751},{"TravelLokaId":9000000958704,"HotelName":"Cozrum Homes Charming Corner 2","Country":"Vietnam","City":"District 3","Address":"453/48 Nguyen Dinh Chieu","Lat":10.7704428,"Lng":106.6827064},{"TravelLokaId":9000000958707,"HotelName":"Cozrum Homes Greena House","Country":"Vietnam","City":"District 1","Address":"74/5 Thạch Thị Thanh, Phường Tân Định, Quận 1, TP. HCM","Lat":10.791244096,"Lng":106.692130351},{"TravelLokaId":9000000958712,"HotelName":"Hotel Du Ciel Dalat","Country":"Vietnam","City":"Da Lat","Address":"Lo 13 Hoang Van Thu","Lat":11.9375698,"Lng":108.429706},{"TravelLokaId":9000000958713,"HotelName":"Seventeen Vung Tau Hotel","Country":"Vietnam","City":"Vung Tau City","Address":"21 Van Cao, Ward 2","Lat":10.3350396,"Lng":107.0841513},{"TravelLokaId":9000000958722,"HotelName":"Cali Hill Resort & Spa","Country":"Vietnam","City":"Phu Quoc","Address":"167 Tran Hung Dao","Lat":10.200422356,"Lng":103.967172626},{"TravelLokaId":9000000958726,"HotelName":"Malina Luxury Hotel","Country":"Vietnam","City":"Da Lat","Address":"lô 1571 Tran Dai Nghia","Lat":11.9675527,"Lng":108.451044},{"TravelLokaId":9000000958754,"HotelName":"Sang Boutique Villa Danang","Country":"Vietnam","City":"Son Tra District","Address":"08 Nguyen Huu Thong","Lat":16.0710355,"Lng":108.2431256},{"TravelLokaId":9000000958758,"HotelName":"AFFA Boutique Hotel","Country":"Vietnam","City":"Hoan Kiem District","Address":"17 Trang Thi, Hang Trong Ward, Hoan Kiem","Lat":21.026124,"Lng":105.8505027},{"TravelLokaId":9000000958768,"HotelName":"Heritage Cruises Cat Ba Archipelago","Country":"Vietnam","City":"Ha Long City","Address":"Lô 26, Tuần Châu Marina, Hạ Long","Lat":20.925665,"Lng":106.982165},{"TravelLokaId":9000000961074,"HotelName":"Sogo Hotel Saigon","Country":"Vietnam","City":"District 1","Address":"357 Pham Ngu Lao, Pham Ngu Lao Ward, District 1","Lat":10.7670799,"Lng":106.6897288},{"TravelLokaId":9000000961834,"HotelName":"The Crystal Apartment - Nha Trang","Country":"Vietnam","City":"Nha Trang","Address":"3 Pham Van Dong, Phuong Vinh Phuoc","Lat":12.2742606,"Lng":109.2018644},{"TravelLokaId":9000000961837,"HotelName":"G9 Hotel Phu Yen","Country":"Vietnam","City":"Tuy Hoa City","Address":"Apec Madala Phu Yen, Hung Vuong Main Street","Lat":13.1035822,"Lng":109.3071594},{"TravelLokaId":9000000961866,"HotelName":"86Homestay","Country":"Vietnam","City":"Phan Thiet City","Address":"17 Phùng Hưng","Lat":10.9342723,"Lng":108.1177496},{"TravelLokaId":9000000961869,"HotelName":"Trang An Mountainside Homestay","Country":"Vietnam","City":"Hoa Lu District","Address":"Xuan Ang Noi, Hoa Lu District","Lat":20.2499136,"Lng":105.9384099},{"TravelLokaId":9000000961876,"HotelName":"Seren Camp Tam Hai","Country":"Vietnam","City":"Nui Thanh District","Address":"Lien Xa","Lat":15.4983787,"Lng":108.6432875},{"TravelLokaId":9000000961877,"HotelName":"Soc Con Homestay & Coffee","Country":"Vietnam","City":"Da Lat","Address":"27 An Binh","Lat":11.92578,"Lng":108.43699},{"TravelLokaId":9000000961882,"HotelName":"Ambedo Hotel Phu Quoc","Country":"Vietnam","City":"Phu Quoc","Address":"125 Tran Phu, Duong Dong","Lat":10.2277887,"Lng":103.954773},{"TravelLokaId":9000000961906,"HotelName":"LiLac Hotel Dalat","Country":"Vietnam","City":"Da Lat","Address":"127 Yersin","Lat":11.9499458,"Lng":108.4558894},{"TravelLokaId":9000000961907,"HotelName":"The Aratana Villa Dalat","Country":"Vietnam","City":"Da Lat","Address":"BL 03, Khu quy hoach Thai Lam","Lat":11.928661,"Lng":108.4349526},{"TravelLokaId":9000000961909,"HotelName":"Bao Ngoc Hotel Con Dao","Country":"Vietnam","City":"Con Dao (Hon Son) District","Address":"Slot 2, Phan Chu Trinh","Lat":8.6958932,"Lng":106.6083855},{"TravelLokaId":9000000961910,"HotelName":"Ho Tram Pristine Beach","Country":"Vietnam","City":"Xuyen Moc District, Vung Tau City","Address":"Group 10, Ho Tram","Lat":10.4724654,"Lng":107.4361828},{"TravelLokaId":9000000961911,"HotelName":"Celadon City -  Emerald Precinct DT Apartment","Country":"Vietnam","City":"Tan Phu District","Address":"Celadon City, 88 Bờ Bao Tân Thắng, phường Sơn Kỳ, Quận Tan Phú","Lat":10.803278,"Lng":106.610873},{"TravelLokaId":9000000961918,"HotelName":"Ami Boutique Hotel Da Lat","Country":"Vietnam","City":"Da Lat","Address":"17 Huynh Thuc Khang","Lat":11.9351106,"Lng":108.4283338},{"TravelLokaId":9000000961922,"HotelName":"Happy Hotel & Apartment Vung Tau","Country":"Vietnam","City":"Vung Tau City","Address":"58 Dinh Tien Hoang, Ward 2","Lat":10.3401569,"Lng":107.0778087},{"TravelLokaId":9000000961924,"HotelName":"Rose Hotel","Country":"Vietnam","City":"Gia Nghia Town","Address":"1 Le Thi Hong Gam","Lat":11.9984216,"Lng":107.7010419},{"TravelLokaId":9000000961926,"HotelName":"Moon Le Villa","Country":"Vietnam","City":"Hoi An","Address":"155 Nguyen Duy Hieu, Cam Chau Ward, Hoi An City, Quang Nam province","Lat":15.878289915,"Lng":108.340714574},{"TravelLokaId":9000000961927,"HotelName":"Nguyen's Apartment Da Nang","Country":"Vietnam","City":"Ngu Hanh Son District","Address":"103 Phan Tu","Lat":16.0464578,"Lng":108.2461154},{"TravelLokaId":9000000961935,"HotelName":"Nguyen Nhan Hotel","Country":"Vietnam","City":"Phu Quoc","Address":"127 Tran Hung Dao","Lat":10.199952252,"Lng":103.968330031},{"TravelLokaId":9000000961936,"HotelName":"Comlam EcoHouse","Country":"Vietnam","City":"Sa Pa District","Address":"Ta Van","Lat":22.302577,"Lng":103.886023},{"TravelLokaId":9000000961939,"HotelName":"An Nam 68 Homestay Hoi An","Country":"Vietnam","City":"Hoi An","Address":"68 Nguyen Tri Phuong","Lat":15.87175,"Lng":108.3326987},{"TravelLokaId":9000000961953,"HotelName":"Premier Pearl Hotel Vung Tau","Country":"Vietnam","City":"Vung Tau City","Address":"69 Thuy Van, Ward 2","Lat":10.3322495,"Lng":107.0889669},{"TravelLokaId":9000000961970,"HotelName":"22Housing Apartment 48 Phan Ke Binh","Country":"Vietnam","City":"Ba Dinh District","Address":"48 Phan Ke Binh","Lat":21.0342041,"Lng":105.8134869},{"TravelLokaId":9000000962004,"HotelName":"Hanoi Center Silk Hotel","Country":"Vietnam","City":"Hoan Kiem District","Address":"22A Ta Hien, Hang Buom, Hoan Kiem","Lat":21.034492,"Lng":105.852167},{"TravelLokaId":9000000962078,"HotelName":"Tata Hotel Dalat","Country":"Vietnam","City":"Da Lat","Address":"Lo 37 Khu Quy Hoach Tran Le","Lat":11.9366757,"Lng":108.4270817},{"TravelLokaId":9000000962093,"HotelName":"Dong Nam Hotel Can Tho","Country":"Vietnam","City":"Ninh Kieu District","Address":"1 Nguyen Binh Khiem","Lat":10.042836573,"Lng":105.783153176},{"TravelLokaId":9000000962094,"HotelName":"Hotel 178","Country":"Vietnam","City":"Ninh Kieu District","Address":"178/26/16 3/2 Road","Lat":10.022169564,"Lng":105.76668246},{"TravelLokaId":9000000962202,"HotelName":"An Binh Hotel - Phu Quy Island","Country":"Vietnam","City":"Phu Quy District","Address":"402 Vo Van Kiet","Lat":10.5067894,"Lng":108.9530983},{"TravelLokaId":9000000962296,"HotelName":"View Home Dalat","Country":"Vietnam","City":"Da Lat","Address":"70 Trinh Hoai Duc","Lat":11.946444975,"Lng":108.483274392},{"TravelLokaId":9000000962306,"HotelName":"Swan Hotel Saigon","Country":"Vietnam","City":"District 2","Address":"21 Street 68","Lat":10.7731851,"Lng":106.7567575},{"TravelLokaId":9000000962322,"HotelName":"Song Anh 2 Hotel Sapa","Country":"Vietnam","City":"Sa Pa District","Address":"22 Muong Hoa","Lat":22.3314787,"Lng":103.8443656},{"TravelLokaId":9000000962339,"HotelName":"Le Tung Hotel Khanh Hoa","Country":"Vietnam","City":"Van Ninh District","Address":"2 Dinh Tien Hoang","Lat":12.6911641,"Lng":109.22534},{"TravelLokaId":9000000962357,"HotelName":"The Happy Ride Glamping","Country":"Vietnam","City":"Phan Thiet City","Address":"07 Xuan Thuy, Hon Rom, Mui Ne","Lat":10.9619195,"Lng":108.3242345},{"TravelLokaId":9000000962362,"HotelName":"Avana Retreat","Country":"Vietnam","City":"Mai Chau District","Address":"Panh Village, Bao La Commune","Lat":20.7017927,"Lng":104.945857},{"TravelLokaId":9000000962363,"HotelName":"Lavie House 3 - Biet Thu Bai Sau","Country":"Vietnam","City":"Vung Tau City","Address":"F5 Van Cao","Lat":10.335217855,"Lng":107.083825633},{"TravelLokaId":9000000962378,"HotelName":"House & Caffeine","Country":"Vietnam","City":"District 1","Address":"17/1 Co Giang","Lat":10.7646283,"Lng":106.6969801},{"TravelLokaId":9000000962388,"HotelName":"Hanoi Home 1 - Stylish Homestay","Country":"Vietnam","City":"Tay Ho District","Address":"No 8, Alley 6, Tay Ho Street","Lat":21.0662196,"Lng":105.8246402},{"TravelLokaId":9000000962406,"HotelName":"Mansion Park Hotel & Apartment","Country":"Vietnam","City":"Bien Hoa City","Address":"K73, Area 7","Lat":10.9464842,"Lng":106.829188},{"TravelLokaId":9000000962409,"HotelName":"Sena Home Dragon Bridge Da Nang","Country":"Vietnam","City":"Son Tra District","Address":"3/12 Ha Thi Than. Son Tra District","Lat":16.0602152,"Lng":108.2315195},{"TravelLokaId":9000000962487,"HotelName":"Eden Home & Cafe","Country":"Vietnam","City":"Quy Nhon City","Address":"Lô 79 + 80, Khu Lý Hòa, Nhơn Lý, Thành phố Quy Nhơn, Tỉnh Bình Định","Lat":13.88024342,"Lng":109.291440622},{"TravelLokaId":9000000962505,"HotelName":"Hero Hostel & Billiards","Country":"Vietnam","City":"Chau Doc City","Address":"5A Tran Nguyen Han Street, Chau Quoi 3 Helmet","Lat":10.7069028,"Lng":105.123885},{"TravelLokaId":9000000962508,"HotelName":"Tashi Boutique Danang","Country":"Vietnam","City":"Son Tra District","Address":"98 Le Thuoc","Lat":16.0769308,"Lng":108.240167},{"TravelLokaId":9000000962515,"HotelName":"Chai Bo Boutique Room","Country":"Vietnam","City":"Da Lat","Address":"40/32 Ma Trang Son","Lat":11.9421716,"Lng":108.4232467},{"TravelLokaId":9000000962547,"HotelName":"Lavie House 11 - Bãi Sau Vũng Tàu (deactivated)","Country":"Vietnam","City":"Vung Tau City","Address":"F8 Thai Van Lung","Lat":10.335726572,"Lng":107.083717287},{"TravelLokaId":9000000962886,"HotelName":"Brown House Resort","Country":"Vietnam","City":"Phong Dien District","Address":"My Thuan, My Khanh","Lat":9.9983647,"Lng":105.7057792},{"TravelLokaId":9000000962913,"HotelName":"Rich Can Tho Hotel","Country":"Vietnam","City":"Ninh Kieu District","Address":"86D Hung Vuong","Lat":10.0427717,"Lng":105.7781903},{"TravelLokaId":9000000962934,"HotelName":"A25 Hotel - 386 Hai Ba Trung Dalat","Country":"Vietnam","City":"Da Lat","Address":"386 Hai Ba Trung","Lat":11.9547878,"Lng":108.4302823},{"TravelLokaId":9000000962954,"HotelName":"NGO Homestay Phan Thiet","Country":"Vietnam","City":"Phan Thiet City","Address":"Nguyen Trai, Phu Thuy, Phan Thiet, Binh Thuan","Lat":10.931515398,"Lng":108.114032624},{"TravelLokaId":9000000962991,"HotelName":"Amy Dongdo Plaza Hotel","Country":"Vietnam","City":"Bac Ninh City","Address":"5 Le Thai To","Lat":21.170055876,"Lng":106.060002879},{"TravelLokaId":9000000963027,"HotelName":"Hon Cau Resort","Country":"Vietnam","City":"Tuy Phong District","Address":"10 Quoc Lo 1A, Vinh Tan","Lat":11.3284517,"Lng":108.8400837}]