[{"TravelLokaId":1000000397065,"HotelName":"Hoa Mai Hotel","Country":"Vietnam","City":"District 10","Address":"723-725 Le Hong Phong","Lat":10.7740111,"Lng":106.6717464},{"TravelLokaId":1000000430295,"HotelName":"Rainbow Hotel 2","Country":"Vietnam","City":"District 11","Address":"618 Nguyen Chi Thanh Street","Lat":10.758153,"Lng":106.659055},{"TravelLokaId":1000000438622,"HotelName":"Camel Hotel","Country":"Vietnam","City":"Hoan Kiem District","Address":"8/50 Dao Duy Tu","Lat":21.035347,"Lng":105.852482},{"TravelLokaId":1000000449028,"HotelName":"Yasaka Huong Sen Restaurant & Hotel","Country":"Vietnam","City":"Tuy Hoa City","Address":"22B Nguyen Tat Thanh Street","Lat":13.08465,"Lng":109.300754},{"TravelLokaId":1000000466048,"HotelName":"Royal Hotel Ha Long","Country":"Vietnam","City":"Ha Long City","Address":"144 Tran Quoc Nghien","Lat":20.937681949,"Lng":107.122332534},{"TravelLokaId":1000000505038,"HotelName":"Huong Toan Eco Resort","Country":"Vietnam","City":"Phu Quoc","Address":"Group 7, Ben Tram Hamlet, Cua Duong, Phu Quoc, Kien Giang, Vietnam","Lat":10.244367,"Lng":104.01747},{"TravelLokaId":1000000536014,"HotelName":"Emis Hotel","Country":"Vietnam","City":"Phu Quoc","Address":"Group 5, Suoi May Hamlet, Duong To","Lat":10.17898,"Lng":103.983968},{"TravelLokaId":1000000547235,"HotelName":"Tahiti Resort","Country":"Vietnam","City":"Phu Quoc","Address":"90 Tran Hung Dao, Duong Dong Town","Lat":10.203112,"Lng":103.964099},{"TravelLokaId":1000000554716,"HotelName":"Thien Phu Nghia Guest House","Country":"Vietnam","City":"Phu Quoc","Address":"174/1, 30/4 Street, Duong Dong Town (Nhà Nghỉ Thiên Phú Nghĩa)","Lat":10.2155832,"Lng":103.9731627},{"TravelLokaId":1000000561052,"HotelName":"Phi Phung Hotel","Country":"Vietnam","City":"Tan Binh District","Address":"297 Le Van Sy","Lat":10.7947424,"Lng":106.6675204},{"TravelLokaId":1000000572379,"HotelName":"Nhat Vy Hotel Dalat","Country":"Vietnam","City":"Da Lat","Address":"12 Hoang Hoa Tham","Lat":11.938917,"Lng":108.46292},{"TravelLokaId":1000000590995,"HotelName":"The Field Homestay","Country":"Vietnam","City":"Hoi An","Address":"Group 3, Thanh Nhut, Cam Thanh 2","Lat":15.8755755,"Lng":108.363072},{"TravelLokaId":1000000593877,"HotelName":"Thanh Hoang Chau Hotel","Country":"Vietnam","City":"Hai Chau District","Address":"56 Hoang Dieu","Lat":16.065022,"Lng":108.219027},{"TravelLokaId":1000000601300,"HotelName":"Up Village Phu Quoc","Country":"Vietnam","City":"Phu Quoc","Address":"Area 4, Cua Lap, Duong To, Duong Dong, Phu Quoc, Vietnam","Lat":10.187523,"Lng":103.968805},{"TravelLokaId":1000000604327,"HotelName":"Hanoi Amore Hotel & Travel","Country":"Vietnam","City":"Thanh Xuan District","Address":"105 Vu Tong Phan Street","Lat":20.99667164,"Lng":105.816568136},{"TravelLokaId":1000000617879,"HotelName":"Star City Riverside Hotel by Haviland","Country":"Vietnam","City":"Son Tra District","Address":"147-149 Tran Hung Dao","Lat":16.08429,"Lng":108.228952},{"TravelLokaId":1000000797741,"HotelName":"iBeach Apartment - Muong Thanh Vien Trieu","Country":"Vietnam","City":"Nha Trang","Address":"3 -5 Pham Van Dong","Lat":12.2742607,"Lng":109.2018644},{"TravelLokaId":1000000910850,"HotelName":"Justay Luxury Apartment Da Nang","Country":"Vietnam","City":"Son Tra District","Address":"120 Vo Nguyen Giap","Lat":16.077626,"Lng":108.2452123},{"TravelLokaId":2000000200388,"HotelName":"Moon View Hotel 2","Country":"Vietnam","City":"Ba Dinh District","Address":"61 Hang Than","Lat":21.041597,"Lng":105.847627},{"TravelLokaId":2000000261755,"HotelName":"Hoang Ngoc Hotel 2","Country":"Vietnam","City":"Hai Ba Trung District","Address":"19 Nguyen Thuong Hien","Lat":21.018852,"Lng":105.842697},{"TravelLokaId":2000000285030,"HotelName":"Ruby Hotel Nha Trang","Country":"Vietnam","City":"Nha Trang","Address":"14 Tran Phu","Lat":12.2197514,"Lng":109.2039647},{"TravelLokaId":3000010019060,"HotelName":"Thanh Thu Hotel","Country":"Vietnam","City":"District 1","Address":"34 Nguyen An Ninh","Lat":10.773292,"Lng":106.696873},{"TravelLokaId":3000010019123,"HotelName":"Bach Mai Hotel","Country":"Vietnam","City":"District 1","Address":"152 Cong Quynh","Lat":10.765768,"Lng":106.691569},{"TravelLokaId":3000010019448,"HotelName":"Villa Sim","Country":"Vietnam","City":"Dong Hoi City","Address":"Vo Nguyen Giap Street","Lat":17.459748,"Lng":106.644432},{"TravelLokaId":3000010019901,"HotelName":"Hoa Sen Hotel Da Lat 62","Country":"Vietnam","City":"Da Lat","Address":"62 Phan Dinh Phung","Lat":11.944745,"Lng":108.43647},{"TravelLokaId":3000010019913,"HotelName":"Phuong Hoang Hotel","Country":"Vietnam","City":"Van Don District","Address":"Dong Nam Village, Quan Lan, Van Đon","Lat":20.876302061,"Lng":107.490930175},{"TravelLokaId":3000010020308,"HotelName":"Queen Bee Hotel","Country":"Vietnam","City":"District 7","Address":"R4- 27,28 Hung Gia 5 St., PMH, Dist. 7","Lat":10.7323992,"Lng":106.7077534},{"TravelLokaId":3000010020491,"HotelName":"Trang Nhung Hotel Vung Tau","Country":"Vietnam","City":"Vung Tau City","Address":"49 La Van Cau","Lat":10.33869,"Lng":107.0891545},{"TravelLokaId":3000010020513,"HotelName":"Organic Garden Hostel","Country":"Vietnam","City":"Da Lat","Address":"23 Thien Y street","Lat":11.937971,"Lng":108.424694},{"TravelLokaId":3000010020523,"HotelName":"Gia Loi Hotel","Country":"Vietnam","City":"Lien Chieu District","Address":"492 Kinh Duong Vuong","Lat":16.0821533,"Lng":108.1585236},{"TravelLokaId":3000010021220,"HotelName":"Bui Hostel","Country":"Vietnam","City":"Rach Gia City","Address":"236 Nguyen Hung Son","Lat":10.0081028,"Lng":105.0801248},{"TravelLokaId":3000010021359,"HotelName":"Rung Hoa Hotel Dalat","Country":"Vietnam","City":"Da Lat","Address":"7A/1 Mai Anh Dao","Lat":11.981497,"Lng":108.453216},{"TravelLokaId":3000010021535,"HotelName":"Ngoc Chau Hotel Dalat","Country":"Vietnam","City":"Da Lat","Address":"23 Nam Ky Khoi Nghia, Ward 1","Lat":11.9405842,"Lng":108.43582},{"TravelLokaId":3000010021536,"HotelName":"Bostand 2 Hotel Danang","Country":"Vietnam","City":"Son Tra District","Address":"91 Ha Bong","Lat":16.066176,"Lng":108.244458},{"TravelLokaId":3000010021603,"HotelName":"Thanh Van Hostel","Country":"Vietnam","City":"Son Tra District","Address":"05 Le Duc Tho","Lat":16.104420636,"Lng":108.25557375},{"TravelLokaId":3000010021636,"HotelName":"Sapa May Ho Hotel","Country":"Vietnam","City":"Sa Pa District","Address":"5 Kim Dong Street","Lat":22.337551,"Lng":103.847786},{"TravelLokaId":3000010021637,"HotelName":"Furuya House","Country":"Vietnam","City":"Ba Dinh District","Address":"No 12, Alley 71, Linh Lang","Lat":21.0336656,"Lng":105.8103251},{"TravelLokaId":3000010021641,"HotelName":"Sen Vang Hotel","Country":"Vietnam","City":"Son Tra District","Address":"173 Ho Nghinh","Lat":16.0661712,"Lng":108.2432793},{"TravelLokaId":3000010021675,"HotelName":"Sunna Hotel Danang","Country":"Vietnam","City":"Son Tra District","Address":"27 Duong Dinh Nghe, Phuoc My","Lat":16.068691,"Lng":108.243517},{"TravelLokaId":3000010021719,"HotelName":"Son Hien Hotel Cam Ranh","Country":"Vietnam","City":"Nha Trang","Address":"Highway 1A","Lat":12.083929,"Lng":109.154808},{"TravelLokaId":3000010021749,"HotelName":"Beepub","Country":"Vietnam","City":"Da Lat","Address":"74 Truong Cong Dinh","Lat":11.944732,"Lng":108.434846},{"TravelLokaId":3000010021759,"HotelName":"Phu Nguyen Hotel","Country":"Vietnam","City":"Nha Trang","Address":"02 Phan Phu Tien","Lat":12.281757,"Lng":109.19942},{"TravelLokaId":3000010021783,"HotelName":"O La Guest House","Country":"Vietnam","City":"Hoi An","Address":"12 Tran Binh Trong, Cam Chau","Lat":15.8829517,"Lng":108.3482677},{"TravelLokaId":3000010022001,"HotelName":"Hai Khanh Hotel","Country":"Vietnam","City":"Hai Duong City","Address":"100 Ham Nghi Street,","Lat":20.9299772,"Lng":106.3370079},{"TravelLokaId":3000010022008,"HotelName":"Golden Sun Sapa","Country":"Vietnam","City":"Sa Pa District","Address":"075 Thach Son Street","Lat":22.336238,"Lng":103.846058},{"TravelLokaId":3000010022046,"HotelName":"Kim Quang Apartment","Country":"Vietnam","City":"Vung Tau City","Address":"Kim To Tower, Hoa Hong Street, Phuoc Tinh","Lat":10.407518773,"Lng":107.19396743},{"TravelLokaId":3000010022138,"HotelName":"The Opera Hotel Hai Phong","Country":"Vietnam","City":"Hong Bang District","Address":"20B Minh Khai, Hoang Van Thu, Hong Bang","Lat":20.860817,"Lng":106.685084},{"TravelLokaId":3000010022260,"HotelName":"Phuong Nam Hotel Dien Bien","Country":"Vietnam","City":"Dien Bien Phu City","Address":"211 Group 3","Lat":21.397299,"Lng":103.019125},{"TravelLokaId":3000010022269,"HotelName":"Hoa Dao Hotel","Country":"Vietnam","City":"Hoa Binh City","Address":"Le Thanh Ton","Lat":20.8281145,"Lng":105.3376169},{"TravelLokaId":3000010022421,"HotelName":"Kim Quang Villa","Country":"Vietnam","City":"Vung Tau City","Address":"B27 Hoa Sen, Kim To Villa, Phuoc Tinh","Lat":10.405988328,"Lng":107.193973017},{"TravelLokaId":3000010022539,"HotelName":"Cong Doan Danang Hotel (Danang Trade Union Hotel)","Country":"Vietnam","City":"Hai Chau District","Address":"50 Pasteur Street","Lat":16.069738,"Lng":108.218032},{"TravelLokaId":3000010022559,"HotelName":"DLGL Dung Quat Hotel","Country":"Vietnam","City":"Binh Son District","Address":"Doc Soi, Dung Quat","Lat":15.368312,"Lng":108.725645},{"TravelLokaId":3000010022562,"HotelName":"Nu Hotel","Country":"Vietnam","City":"District 1","Address":"18 Bui Vien","Lat":10.76793,"Lng":106.694853},{"TravelLokaId":3000010022597,"HotelName":"Tan Truong Son Hotel","Country":"Vietnam","City":"Dong Hoi City","Address":"34 Mac Dinh Chi Street","Lat":17.46049,"Lng":106.624679},{"TravelLokaId":3000010022623,"HotelName":"Hoa Binh 2 Hotel","Country":"Vietnam","City":"Hoa Binh City","Address":"395 An Duong Vuong","Lat":20.804298,"Lng":105.335334},{"TravelLokaId":3000010022652,"HotelName":"Hanoi New Airport Hotel","Country":"Vietnam","City":"Soc Son District","Address":"Thon Dong, Phu Minh, Soc Son","Lat":21.193019,"Lng":105.830486},{"TravelLokaId":3000010022679,"HotelName":"Eden Hotel Go Vap","Country":"Vietnam","City":"Go Vap District","Address":"182/45 Le Duc Tho Street, Ward 6, Go Vap","Lat":10.826856,"Lng":106.691736},{"TravelLokaId":3000010022780,"HotelName":"Bach Duong Hotel - Doi Can","Country":"Vietnam","City":"Ba Dinh District","Address":"459 Doi Can","Lat":21.037713,"Lng":105.809668},{"TravelLokaId":3000010022892,"HotelName":"Hoan Kiem Hotel","Country":"Vietnam","City":"Hue City","Address":"1 Nguyen Sinh Sac","Lat":16.475858,"Lng":107.602972},{"TravelLokaId":3000010023005,"HotelName":"Hung Vuong Hotel Phu Yen","Country":"Vietnam","City":"Tuy Hoa City","Address":"239-241 Hung Vuong Street","Lat":13.101476,"Lng":109.308638}]